fyo/__init__.py
fyo/path.py
fyo-0.1.2.dist-info/WHEEL
fyo-0.1.2.dist-info/METADATA
fyo-0.1.2.dist-info/RECORD
